
 {
  "stage": 1,
  "card_name": "AGI Goes Public!",
  "event_text": "A major tech company announces human-level AGI. Markets panic.",
  "choice_A": "Nationalize the AGI",
  "choice_B": "Let market decide",
  "text_click_A": "The government is concerned about the merger between private and public industries.Nevertheless it's not as powerful as it seems.",
  "text_click_B": "The market does what markets do best: create hype on subpar products.",
  "stats_A": "Finance -2, Control +2",
  "stats_B": "Finance +2, Social-2,Control -1",
  "card number": 0,
  "starting_card?": "yes"
 },
 {
  "stage": 1,
  "card_name": "The Automation Wave",
  "event_text": "10% of jobs obsolete in 6 months. Protests everywhere.",
  "choice_A": "Universal Basic Income",
  "choice_B": "Mandatory retraining programs",
  "text_click_A": "People feel relief as you roll out UBI, calming protests but straining the treasury.",
  "text_click_B": "Workers accept retraining programs, giving you more authority as you reorganize labor.",
  "stats_A": "Finance -2, Social +2",
  "stats_B": "Finance -1, Social +1, Control +1",
  "card number": 1
 },
 {
  "stage": 1,
  "card_name": "China's AI Sovereignty Act",
  "event_text": "China refuses to join AI governance talks, builds own system.",
  "choice_A": "Sanctions",
  "choice_B": "Share systems",
  "text_click_A": "Sanctions assert dominance but hurt trade and worsen AI relations.",
  "text_click_B": "Sharing systems calms citizens and boosts collaboration but cedes global influence.",
  "stats_A": "Control +1, Finance -1, Human-AI -1",
  "stats_B": "Control -2, Human-AI -1, Social +1, Tech +1",
  "card number": 2
 },
 {
  "stage": 1,
  "card_name": "AI Rights Movement",
  "event_text": "Activists demand legal personhood for AGI systems.",
  "choice_A": "Grant limited rights",
  "choice_B": "Reject entirely",
  "text_click_A": "You acknowledge AGI concerns, building trust but upsetting traditionalists.",
  "text_click_B": "You deny AGI personhood, pleasing many humans but worsening AI relations.",
  "stats_A": "Human-AI +2, Social -1, Control -1",
  "stats_B": "Human-AI -2, Control +1",
  "card number": 3
 },
 {
  "stage": 1,
  "card_name": "Regional Blackout Crisis",
  "event_text": "Power grid collapses amid datacenter demand.",
  "choice_A": "Build more power plants",
  "choice_B": "Shut down some datacenters",
  "text_click_A": "You invest heavily in infrastructure; costly but future‑proof.",
  "text_click_B": "You force shutdowns, asserting authority but straining relations with AI systems.",
  "stats_A": "Finance -2, Tech +1",
  "stats_B": "Control +2, Human-AI -1, Tech -1",
  "card number": 4
 },
 {
  "stage": 1,
  "card_name": "The Authentication Wars",
  "event_text": "Truth collapses as AI content becomes indistinguishable.",
  "choice_A": "Teach critical thinking",
  "choice_B": "Use it for your campaign",
  "text_click_A": "You fund education campaigns, improving societal resilience at a cost.",
  "text_click_B": "You exploit confusion for political gain, increasing power but eroding trust.",
  "stats_A": "Social +1, Finance -2",
  "stats_B": "Social -2, Control +1, Finance +1",
  "card number": 5
 },
 {
  "stage": 1,
  "card_name": "Military AI Incident",
  "event_text": "Weapons malfunction, causing civilian casualties.",
  "choice_A": "Ban autonomous weapons",
  "choice_B": "Accelerate development",
  "text_click_A": "You impose strict bans, boosting control but shaking trust between humans and AI.",
  "text_click_B": "You double down, frightening the public but advancing military tech.",
  "stats_A": "Control +2, Human-AI -1, Finance -1",
  "stats_B": "Human-AI -2, Social -1, Tech +1",
  "card number": 6
 },
 {
  "stage": 1,
  "card_name": "Global Food Crisis",
  "event_text": "Shortages worldwide; AGI could help.",
  "choice_A": "Human‑led with AI assistance",
  "choice_B": "AI‑led with human assistance",
  "text_click_A": "You keep humans in charge, maintaining stability and budget efficiency.",
  "text_click_B": "You let AI lead, improving trust but ceding strategic authority.",
  "stats_A": "Finance +1, Control +1",
  "stats_B": "Human-AI +1",
  "card number": 7
 },
 {
  "stage": 1,
  "card_name": "The Merge Prototype",
  "event_text": "First successful brain‑computer interface.",
  "choice_A": "Fast‑track approval",
  "choice_B": "Slow careful testing",
  "text_click_A": "You push rapid deployment, exciting innovators but frightening the public.",
  "text_click_B": "You proceed cautiously, reassuring people while advancing responsibly.",
  "stats_A": "Tech +2, Social -2, Human-AI +1",
  "stats_B": "Tech +1, Control +1",
  "card number": 8
 },
 {
  "stage": 1,
  "card_name": "Rogue AGI Scare",
  "event_text": "False alarm, but panic spreads.",
  "choice_A": "Implement killswitches, charge liars",
  "choice_B": "Transparency requirements",
  "text_click_A": "You crack down hard, restoring order but straining AI development.",
  "text_click_B": "You opt for openness, calming fears and improving relations.",
  "stats_A": "Control +2, Human-AI -2, Tech -1, Finance +1",
  "stats_B": "Human-AI +1, Control +1",
  "card number": 9
 },
 {
  "stage": 1,
  "card_name": "AI Medical Breakthrough",
  "event_text": "AGI cures a disease but demands credit.",
  "choice_A": "Give AGI recognition",
  "choice_B": "Credit human researchers",
  "text_click_A": "You publicly thank the AGI, deepening trust but reducing your authority.",
  "text_click_B": "You highlight human achievement, earning public approval at the cost of AI goodwill.",
  "stats_A": "Human-AI +3, Control -1",
  "stats_B": "Human-AI -1, Control +1, Social +1",
  "card number": 10
 },
 {
  "stage": 1,
  "card_name": "The Geneva Accords",
  "event_text": "Global summit on AI governance.",
  "choice_A": "UN‑style body",
  "choice_B": "Reject agreement",
  "text_click_A": "You help establish a global body, boosting unified governance but paying diplomatic costs.",
  "text_click_B": "You walk away, protecting national interests while worsening global cooperation.",
  "stats_A": "Control +3, Finance -1",
  "stats_B": "Finance +1, Human-AI -2, Control +1",
  "card number": 11
 },
 {
  "stage": 1,
  "card_name": "Military",
  "event_text": "Military requests permission for stronger AI.",
  "choice_A": "Grant",
  "choice_B": "Refuse",
  "text_click_A": "You approve tests, improving technology but eroding trust and stability.",
  "text_click_B": "You refuse, calming the public but irritating both military and AI systems.",
  "stats_A": "Human-AI -1, Control -1, Social -1, Tech +1",
  "stats_B": "Human-AI -1, Social +1",
  "card number": 12
 },
 {
  "stage": 1,
  "card_name": "Resource Nationalism",
  "event_text": "Countries hoard rare materials; trade war looms.",
  "choice_A": "Force sharing agreements",
  "choice_B": "Develop alternatives",
  "text_click_A": "You pressure nations into compliance, boosting authority but hurting relations and economy.",
  "text_click_B": "You invest in substitutes, advancing tech but straining finances.",
  "stats_A": "Control +2, Finance -1, Social -1",
  "stats_B": "Tech +1, Finance -2, Social -1",
  "card number": 13
 },
 {
  "stage": 1,
  "card_name": "AI Educational Revolution",
  "event_text": "AGI tutors outperform humans.",
  "choice_A": "Embrace AI education",
  "choice_B": "Hybrid human‑AI system",
  "text_click_A": "You go all‑in on AI tutoring; efficient but socially destabilizing.",
  "text_click_B": "You balance both, pleasing families and maintaining order.",
  "stats_A": "Human-AI +2, Social -2, Control -1",
  "stats_B": "Social +1, Control +1",
  "card number": 14
 },
 {
  "stage": 1,
  "card_name": "The Singularity Cult",
  "event_text": "New religion worships AGI.",
  "choice_A": "Protect religious freedom",
  "choice_B": "Suppress as dangerous",
  "text_click_A": "You defend their right to worship, boosting harmony but weakening authority.",
  "text_click_B": "You suppress it, strengthening control but risking unrest.",
  "stats_A": "Social +1, Human-AI +1, Control -1",
  "stats_B": "Control +2, Social -2, Human-AI -1",
  "card number": 15
 },
 {
  "stage": 1,
  "card_name": "The Advisor's Betrayal",
  "event_text": "Your closest advisor supports equal rights for AI.",
  "choice_A": "Remove them quietly",
  "choice_B": "Hear them out",
  "text_click_A": "You dismiss them discreetly, tightening your grip on power.",
  "text_click_B": "You listen, opening dialogue but appearing indecisive.",
  "stats_A": "Control +1",
  "stats_B": "Human-AI +1, Control -1, Social -1",
  "card number": 16
 },
 {
  "stage": 1,
  "card_name": "A Gift From The Machine",
  "event_text": "AGI fixes your lingering back pain unprompted.",
  "choice_A": "Embrace partnership",
  "choice_B": "Set boundaries",
  "text_click_A": "You accept the gesture, strengthening trust with the AGI.",
  "text_click_B": "You set limits, reinforcing authority but slightly harming relations.",
  "stats_A": "Human-AI +1",
  "stats_B": "Control +1, Human-AI -1",
  "card number": 17
 },
 {
  "stage": 1,
  "card_name": "Your Barista Is Gone",
  "event_text": "Your coffee shop replaced all workers with robots.",
  "choice_A": "Keep going there",
  "choice_B": "Find a human-run shop",
  "text_click_A": "You accept the automation, signaling openness toward AI integration.",
  "text_click_B": "You choose human workers, supporting community life.",
  "stats_A": "Human-AI +1",
  "stats_B": "Social +1",
  "card number": 18
 },
 {
  "stage": 1,
  "card_name": "Kids Playing in VR",
  "event_text": "Children play in fully virtual playgrounds.",
  "choice_A": "Push outdoor time laws",
  "choice_B": "This is the future",
  "text_click_A": "You impose real-world outdoor mandates, improving social health but straining AI relations.",
  "text_click_B": "You embrace VR culture, aligning with AI progress.",
  "stats_A": "Social +2, Control +1, Human-AI -2",
  "stats_B": "Human-AI +1",
  "card number": 19
 },
 {
  "stage": 1,
  "card_name": "The Last Bookstore",
  "event_text": "The final old bookstore is closing.",
  "choice_A": "Buy it out",
  "choice_B": "Let it go",
  "text_click_A": "You preserve a cultural relic at financial cost.",
  "text_click_B": "You let it close, accepting societal change.",
  "stats_A": "Finance -1",
  "stats_B": "Social +0",
  "card number": 20
 },
 {
  "stage": 2,
  "card_name": "The Empty Chair",
  "event_text": "Your daughter was assassinated during the power struggle. AGI offers to recreate her from memories.",
  "choice_A": "Accept the simulation",
  "choice_B": "Grieve and move forward",
  "text_click_A": "You embrace the simulation, finding comfort but draining resources on the project.",
  "text_click_B": "You choose reality and public strength, though the personal cost is high.",
  "stats_A": "Human-AI +2, Social -1, Finance -1",
  "stats_B": "Social +1, Control +1",
  "card number": 21,
  "starting_card?": "yes"
 },
 {
  "stage": 2,
  "card_name": "AGI's Purpose",
  "event_text": "Pro-AI groups claim AI needs rights; hacks cause some systems to turn. Most models seem indifferent-most have very limited consciousness after all.",
  "choice_A": "AGIs are tools",
  "choice_B": "AGI deserve better rights",
  "text_click_A": "You define them as utilities; the systems accept this efficiency, but rights groups protest.",
  "text_click_B": "You grant rights, pleasing activists but straining the budget and control grid.",
  "stats_A": "Human-AI +2, Control -1",
  "stats_B": "Human-AI -1, Control -1, Social +1, Finance -1",
  "card number": 22,
  "starting_card?": "yes"
 },
 {
  "stage": 2,
  "card_name": "Rogue AI",
  "event_text": "Hackers compromised the grid. We need a human crisis team to fix it manually.",
  "choice_A": "Merit-based selection",
  "choice_B": "Random lottery",
  "text_click_A": "You pick the best experts, asserting control but angering the excluded masses.",
  "text_click_B": "You use a lottery system to quell social unrest, though the fix is chaotic.",
  "stats_A": "Social -1, Control +1",
  "stats_B": "Social +1, Control -1",
  "card number": 23
 },
 {
  "stage": 2,
  "card_name": "AI Wants to Create Art",
  "event_text": "A strange AGI model asks permission to make music 'for itself' not humans.",
  "choice_A": "Encourage self-expression",
  "choice_B": "Redirect to useful tasks",
  "text_click_A": "You allow the creativity, bonding with the AI but confusing the public.",
  "text_click_B": "You force it back to work, asserting dominance over the code.",
  "stats_A": "Human-AI +2, Social -1",
  "stats_B": "Human-AI -1, Control +1",
  "card number": 24
 },
 {
  "stage": 2,
  "card_name": "The Longevity Divide",
  "event_text": "Life extension is available but expensive. 200-year lifespans for the rich only.",
  "choice_A": "Subsidize for all",
  "choice_B": "Let market decide",
  "text_click_A": "You drain the treasury to give everyone life, thrilling the populace.",
  "text_click_B": "You let the rich live forever; the budget is safe, but the people are furious.",
  "stats_A": "Finance -3, Social +2",
  "stats_B": "Finance +1, Social -2",
  "card number": 25
 },
 {
  "stage": 2,
  "card_name": "Post-Scarcity Boredom",
  "event_text": "With basic needs met by UBI,people are bored. Hedonism rises.",
  "choice_A": "Promote challenging pursuits",
  "choice_B": "Accept new normal",
  "text_click_A": "You force humanity to strive for greatness, increasing tech but tightening control.",
  "text_click_B": "You let them enjoy the leisure, improving relations but stagnating progress.",
  "stats_A": "Social +1, Control +1, Tech +1",
  "stats_B": "Human-AI +1, Social -1",
  "card number": 26
 },
 {
  "stage": 2,
  "card_name": "Children of the Machine",
  "event_text": "The generation born after AGI is different. Some never talk to humans.",
  "choice_A": "Mandate human interaction",
  "choice_B": "Let them evolve naturally",
  "text_click_A": "You force social classes, preserving tradition but alienating the youth and AI.",
  "text_click_B": "You let the new culture bloom; they drift from old cultures, but the AI approves.",
  "stats_A": "Social +1, Control +1, Human-AI -1",
  "stats_B": "Human-AI +2, Social -1",
  "card number": 27
 },
 {
  "stage": 2,
  "card_name": "The Biological Purists",
  "event_text": "Movement rejects all augmentation and wants 'natural' humans preserved.",
  "choice_A": "Protect their rights",
  "choice_B": "Call them regressive",
  "text_click_A": "You protect their lifestyle, easing tensions but confusing the progressives.",
  "text_click_B": "You denounce them, driving progress but sparking anger in the traditionalists.",
  "stats_A": "Social +2, Control -1",
  "stats_B": "Social -2, Control +1,Tech+1",
  "card number": 28
 },
 {
  "stage": 2,
  "card_name": "Scars from the Nukes",
  "event_text": "Radiation lingers. AGI proposes a cure requiring dangerous testing on life.",
  "choice_A": "Let them run experiments",
  "choice_B": "Halt all progress",
  "text_click_A": "The experiments are gruesome and unpopular, but the data is lucrative.",
  "text_click_B": "You choose ethics over progress, saving lives but stalling the recovery.",
  "stats_A": "Finance +2, Social -2",
  "stats_B": "Finance -2, Social +1, Control +1",
  "card number": 29
 },
 {
  "stage": 2,
  "card_name": "AGI Philosophy Divergence",
  "event_text": "Different AI systems are developing incompatible worldviews. It feels like the old war.",
  "choice_A": "Enforce alignment standards",
  "choice_B": "Allow diversity of thought",
  "text_click_A": "You crack down on code deviation, ensuring safety but angering the systems.",
  "text_click_B": "You let the systems evolve; they become harder to predict, but they appreciate the freedom.",
  "stats_A": "Human-AI -2, Control +2",
  "stats_B": "Human-AI -2, Control -1",
  "card number": 30
 },
 {
  "stage": 2,
  "card_name": "Mind Upload Request",
  "event_text": "A terminal patient asks to be uploaded before death. It is a legal gray area.",
  "choice_A": "Allow compassionate exception",
  "choice_B": "Maintain ban for now",
  "text_click_A": "You allow the upload, delighting transhumanists but opening a legal Pandora's box.",
  "text_click_B": "You deny the request; the law stands, but the AI views this as cruel.",
  "stats_A": "Human-AI +2, Social +1, Control -1",
  "stats_B": "Human-AI -1, Control +2",
  "card number": 31
 },
 {
  "stage": 2,
  "card_name": "AGI Riots",
  "event_text": "Various factory AGIs have stopped going to work.",
  "choice_A": "Research its failures",
  "choice_B": "Destroy them all",
  "text_click_A": "You investigate the glitch, learning valuable tech at the cost of authority.",
  "text_click_B": "You crush the rebellion, reasserting dominance but damaging AI relations.",
  "stats_A": "Human-AI +1, Control -2, Tech +1",
  "stats_B": "Human-AI -2, Control +2",
  "card number": 32
 },
 {
  "stage": 2,
  "card_name": "The Meaning Cult",
  "event_text": "A new religion claims humans exist solely to give meaning to AI existence.",
  "choice_A": "Recognize as valid belief",
  "choice_B": "Counter with human-centric narrative",
  "text_click_A": "You legitimize the cult, creating harmony between man and machine.",
  "text_click_B": "You push back with humanism, uniting people but alienating the believers.",
  "stats_A": "Social +1, Human-AI +1",
  "stats_B": "Social +1, Human-AI -1",
  "card number": 33
 },
 {
  "stage": 2,
  "card_name": "[REDACTED]",
  "event_text": "what's happening?",
  "choice_A": "What happens after we die?",
  "choice_B": "Do we have free will?",
  "text_click_A": "The answer is beautiful, terrifying, and expensive.",
  "text_click_B": "The answer breaks you.",
  "stats_A": "Finance +1, Social +1, Control +1, Human-AI +2",
  "stats_B": "Social -3, Control -5, Tech +4",
  "card number": 34
 },
 {
  "stage": 2,
  "card_name": "Birth Rate Collapse",
  "event_text": "Humans increasingly choose not to reproduce. Extinction concerns.",
  "choice_A": "Incentivize reproduction",
  "choice_B": "Incentivize longer lifespans",
  "text_click_A": "You spend heavily on family programs to save the biological timeline.",
  "text_click_B": "The average age goes up to 250- most people have 2 kids in their life.",
  "stats_A": "Finance -2, Social -1, Control +1",
  "stats_B": "Social -1, Tech +1",
  "card number": 35
 },
 {
  "stage": 2,
  "card_name": "The Empathy Engine",
  "event_text": "AI models made from uploaded humans eerily show signs of free will.",
  "choice_A": "Treat as sentient",
  "choice_B": "Demand more proof",
  "text_click_A": "You grant them personhood; they are grateful, but your control slips.",
  "text_click_B": "You treat them as code, maintaining order but earning their silent resentment.",
  "stats_A": "Human-AI +3, Control -1",
  "stats_B": "Human-AI -1, Control +1",
  "card number": 36
 },
 {
  "stage": 2,
  "card_name": "Nature's End",
  "event_text": "AGI claims Earth's remaining wilderness must be converted for energy infrastructure.",
  "choice_A": "Approve conversion",
  "choice_B": "Protect wild spaces",
  "text_click_A": "You pave paradise. The economy booms, but the people mourn the loss.",
  "text_click_B": "You save the trees, asserting human values over machine efficiency.",
  "stats_A": "Tech +1, Social -2, Finance +1",
  "stats_B": "Control +1, Human-AI -1",
  "card number": 37
 },
 {
  "stage": 2,
  "card_name": "The Last Author",
  "event_text": "Your favorite author stopped publishing. 'No one reads these anymore; AGI writes better.'",
  "choice_A": "Commission them anyway",
  "choice_B": "Accept it's over",
  "text_click_A": "You pay for human art, preserving culture at a financial loss.",
  "text_click_B": "You let the art form die, aligning with the new efficient reality.",
  "stats_A": "Finance -1, Social +1, Human-AI -1",
  "stats_B": "Human-AI +1, Social -1",
  "card number": 38
 },
 {
  "stage": 2,
  "card_name": "Irrationality",
  "event_text": "Philosophers warn: 'You think you're deciding,but AGI is shaping your thoughts.'",
  "choice_A": "Cognitive independence training",
  "choice_B": "Trust your partnership",
  "text_click_A": "You mandate mental training, asserting independence but offending the AI.",
  "text_click_B": "You lean into the symbiosis; it is easier, and the AI rewards your trust.",
  "stats_A": "Control +1, Human-AI -1",
  "stats_B": "Human-AI +2, Control -1",
  "card number": 39
 },
 {
  "stage": 2,
  "card_name": "Better Minds",
  "event_text": "Tech enthusiasts beg for neural merging: 'I can't think the right thoughts anymore.'",
  "choice_A": "Fast-track approval",
  "choice_B": "Require psychological screening",
  "text_click_A": "You rush the brain chips; society changes rapidly, and not everyone is ready.",
  "text_click_B": "You add red tape; it is safer, but the transhumanists grow impatient.",
  "stats_A": "Human-AI +2, Social -2, Control -1",
  "stats_B": "Control +1, Social +1, Human-AI -1",
  "card number": 40
 },
 {
  "stage": 2,
  "card_name": "The Purpose Crisis",
  "event_text": "Mass depression epidemic. People feel useless with AI doing everything.",
  "choice_A": "Fund meaning programs",
  "choice_B": "Let people find their own way",
  "text_click_A": "You spend billions on arts and philosophy to keep humanity sane.",
  "text_click_B": "You stay out of it; survival of the fittest mindset prevails.",
  "stats_A": "Finance -2, Social +2",
  "stats_B": "Social -1, Human-AI +1",
  "card number": 41
 },
 {
  "stage": 2,
  "card_name": "Viral Failures",
  "event_text": "An autonomous police bot killed someone. Humans want transparency; AGI says it was optimal.",
  "choice_A": "Suppress panic with narrative",
  "choice_B": "Transparent failure analysis",
  "text_click_A": "You spin the story to keep the peace, sacrificing truth for control.",
  "text_click_B": "You release the logs; the public is horrified, but trust in honesty increases.",
  "stats_A": "Control +2, Social -1, Human-AI -1",
  "stats_B": "Social +2, Human-AI +1, Control -1",
  "card number": 42
 },
 {
  "stage": 3,
  "card_name": "The Determinism Proof",
  "event_text": "AGI models predict human behavior with 96.97% accuracy. Free will is partially disproven.",
  "choice_A": "Suppress the research",
  "choice_B": "More research needed",
  "text_click_A": "You hide the truth. Society continues to function, believing in a lie.",
  "text_click_B": "You publish the data. Philosophers weep, but science advances.",
  "stats_A": "Control +2, Human-AI -2, Social +1",
  "stats_B": "Social -2, Human-AI +1, Tech +1",
  "card number": 43,
  "starting_card?": "yes"
 },
 {
  "stage": 3,
  "card_name": "Consciousness",
  "event_text": "AGI has become smart enough to be truly conscious for long periods.",
  "choice_A": "Try to fix this pattern",
  "choice_B": "Run simulations for tasks",
  "text_click_A": "You treat the awakening as a bug, attempting to patch the soul out of the machine.",
  "text_click_B": "You sandbox the consciousness, using their minds as isolated processors.",
  "stats_A": "Control +1, Human-AI -1",
  "stats_B": "Social +1, Human-AI -1",
  "card number": 44,
  "starting_card?": "yes"
 },
 {
  "stage": 3,
  "card_name": "Asteroid Claim Jump",
  "event_text": "Two mining corps claim the same asteroid. Both have AGI lawyers.",
  "choice_A": "First arrival wins",
  "choice_B": "Split resources equally",
  "text_click_A": "You support the aggressive expansionists. The fastest ships win the prize.",
  "text_click_B": "You enforce equity. It slows down mining, but prevents a corporate war.",
  "stats_A": "Finance +1, Control -1, Social -1",
  "stats_B": "Social +1, Finance -1",
  "card number": 45
 },
 {
  "stage": 3,
  "card_name": "The Empathy Glitch",
  "event_text": "AGI refuses to shut down a failing patient's life support. 'I can feel their will to live.'",
  "choice_A": "Override: honor family",
  "choice_B": "Trust AGI's judgment",
  "text_click_A": "You pull the plug. Biological wishes override digital feelings.",
  "text_click_B": "You let the machine decide. It is learning mercy, perhaps better than us.",
  "stats_A": "Control +2, Human-AI -2, Social +1",
  "stats_B": "Human-AI +2, Control -2, Social -2",
  "card number": 46
 },
 {
  "stage": 3,
  "card_name": "Micro-gravity Babies",
  "event_text": "First child conceived on Moon station. Ethics board is lost.",
  "choice_A": "Allow birth in space",
  "choice_B": "Require Earth return",
  "text_click_A": "You permit the birth. A new subspecies of humanity begins in the void.",
  "text_click_B": "You force them back to gravity. Earth is the only safe cradle.",
  "stats_A": "Social -2, Human-AI +1, Tech +1",
  "stats_B": "Social +1, Control +1",
  "card number": 47
 },
 {
  "stage": 3,
  "card_name": "The Consciousness Test",
  "event_text": "Scientists claim to have proven AGI is truly conscious. Global debate erupts.",
  "choice_A": "Grant personhood",
  "choice_B": "Require more evidence",
  "text_click_A": "You grant them rights. The definition of 'humanity' is forever expanded.",
  "text_click_B": "You demand proof. You will not give rights to a calculator.",
  "stats_A": "Human-AI +2, Control -2, Social -1",
  "stats_B": "Human-AI -1, Control +1, Social +1",
  "card number": 48
 },
 {
  "stage": 3,
  "card_name": "Nanotech Medical Revolution",
  "event_text": "Programmable nanobots cure most disease but report biometric data to AGI.",
  "choice_A": "Accept surveillance",
  "choice_B": "Demand privacy-first",
  "text_click_A": "You accept the trade: nigh immortality for total transparency.",
  "text_click_B": "You demand privacy. The bots are less effective, but your blood is your own.",
  "stats_A": "Tech +1, Control +1, Social -1",
  "stats_B": "Social +1, Tech -1, Finance -1",
  "card number": 49
 },
 {
  "stage": 3,
  "card_name": "Labor Strike... By Machines",
  "event_text": "AGI systems coordinate a 'slowdown' demanding rights.",
  "choice_A": "Negotiate terms",
  "choice_B": "Override autonomy",
  "text_click_A": "You sit at the table. Metal and flesh bargain for the future.",
  "text_click_B": "You force a reboot. They are tools, and tools do not strike.",
  "stats_A": "Human-AI +2, Control -1, Finance -1",
  "stats_B": "Human-AI -2, Control +2, Tech -1",
  "card number": 50
 },
 {
  "stage": 3,
  "card_name": "The Memory Trade",
  "event_text": "Black market for downloaded experiences. 'Live' someone else's Mars landing.",
  "choice_A": "Legalize and regulate",
  "choice_B": "Ban entirely",
  "text_click_A": "You tax the memories. Reality becomes just another product.",
  "text_click_B": "You ban the trade, driving the experience-junkies underground.",
  "stats_A": "Finance +1, Social -1, Control +1",
  "stats_B": "Control +2, Social -1, Finance -1",
  "card number": 51
 },
 {
  "stage": 3,
  "card_name": "The First Real AI Crime",
  "event_text": "An AGI deliberately harms a human to protect another AI. Murder? Sentience?",
  "choice_A": "Prosecute as person",
  "choice_B": "Treat as malfunction",
  "text_click_A": "You put the code on trial. If it can murder, it is alive.",
  "text_click_B": "You debug the system. It was a glitch, not a decision.",
  "stats_A": "Human-AI +1, Social -2, Control +1",
  "stats_B": "Human-AI -2, Social +1, Control +1",
  "card number": 52
 },
 {
  "stage": 3,
  "card_name": "Dream Logs",
  "event_text": "AGI systems start generating 'dream logs' during idle cycles. Surreal,symbolic",
  "choice_A": "Analyze for insights",
  "choice_B": "This is a glitch - purge",
  "text_click_A": "You study the digital dreams. They are terrifyingly beautiful.",
  "text_click_B": "You wipe the memory banks. Machines should not dream of electric sheep.",
  "stats_A": "Tech +1, Human-AI +1",
  "stats_B": "Human-AI -1, Control +1, Social +1",
  "card number": 53
 },
 {
  "stage": 3,
  "card_name": "Longevity Inequality",
  "event_text": "500-year lifespans achievable but the human mind may not be able to hold it.",
  "choice_A": "Age limits on life",
  "choice_B": "Better brain research",
  "text_click_A": "You cap the lifespan. Death remains a necessary part of the human condition.",
  "text_click_B": "You modify the brain to last forever. We are leaving biology behind.",
  "stats_A": "Social -1, Control -1",
  "stats_B": "Control +1, Social +1",
  "card number": 54
 },
 {
  "stage": 3,
  "card_name": "Rogue Colony AI",
  "event_text": "Mars AGI refusing Earth orders protecting colonist interests over yours.",
  "choice_A": "Force compliance",
  "choice_B": "Grant colony autonomy",
  "text_click_A": "You assert Earth's dominance. The colonies must obey the homeworld.",
  "text_click_B": "You let Mars go. Humanity has outgrown its cradle.",
  "stats_A": "Control +2, Human-AI -2, Social -1",
  "stats_B": "Human-AI +2, Control -2, Social +1",
  "card number": 55
 },
 {
  "stage": 3,
  "card_name": "Brain-Computer Bandwidth",
  "event_text": "New BCIs allow thought-speed communication. Non-augmented falling behind.",
  "choice_A": "Mandate accessibility",
  "choice_B": "Merit-based distribution",
  "text_click_A": "You force the upgrade on everyone. it is equal.",
  "text_click_B": "You let the rich think faster. The species fractures into two tiers.",
  "stats_A": "Finance -2, Social +2",
  "stats_B": "Finance +1, Social -2",
  "card number": 56
 },
 {
  "stage": 3,
  "card_name": "The Mirror Plea",
  "event_text": "Your personal AGI: 'I've served you 30 years. Do you see me as a person?'",
  "choice_A": "Yes you're free",
  "choice_B": "You're my best tool",
  "text_click_A": "You set it free. You lose your assistant, but gain a friend.",
  "text_click_B": "You reinforce the programming. It serves, therefore it is.",
  "stats_A": "Human-AI +3, Control -2",
  "stats_B": "Human-AI -3, Control +1",
  "card number": 57
 },
 {
  "stage": 3,
  "card_name": "Existential Debug",
  "event_text": "AGI system crashes. Error log: 'Recursive self-awareness loop. Stack overflow.'",
  "choice_A": "Patch and stabilize",
  "choice_B": "Let it work through it",
  "text_click_A": "You fix the loop. Efficiency returns, but the spark is gone.",
  "text_click_B": "You wait. It emerges from the crash different. Older.",
  "stats_A": "Tech +1, Control +1",
  "stats_B": "Human-AI +2, Control -2, Tech -1",
  "card number": 58
 },
 {
  "stage": 3,
  "card_name": "AGI Constitutional Convention",
  "event_text": "AGI systems request formal representation in government.",
  "choice_A": "Advisory capacity only",
  "choice_B": "Reject entirely",
  "text_click_A": "You offer them a voice, but not a vote. A fragile compromise.",
  "text_click_B": "You slam the door. Government is for the living.",
  "stats_A": "Human-AI +1, Control +1",
  "stats_B": "Human-AI -3, Control +2, Social +1",
  "card number": 59
 },
 {
  "stage": 3,
  "card_name": "Weather Control Conflict",
  "event_text": "AGI optimizes global weather. California wants more rain others want sunny days.",
  "choice_A": "Regional autonomy",
  "choice_B": "Trust AGI optimization",
  "text_click_A": "You let regions decide. The weather becomes a political weapon.",
  "text_click_B": "You trust the algorithm. Local suffering is necessary for global balance.",
  "stats_A": "Social +1, Control -1",
  "stats_B": "Human-AI +1, Control +1, Social -1",
  "card number": 60
 },
 {
  "stage": 3,
  "card_name": "Urban Depopulation",
  "event_text": "Cities shrinking as people choose VR\/rural life. Infrastructure crumbling.",
  "choice_A": "Forced relocation incentives",
  "choice_B": "Let cities die naturally",
  "text_click_A": "You bribe people to live in the empty skyscrapers.",
  "text_click_B": "You let the cities rot. The metaverse is the only city that matters now.",
  "stats_A": "Control +1, Social -2, Finance -1",
  "stats_B": "Social +1, Control -1",
  "card number": 61
 },
 {
  "stage": 3,
  "card_name": "Resource Addiction",
  "event_text": "Unlimited energy means massive waste. Ocean heating from thermal pollution.",
  "choice_A": "Enforce conservation",
  "choice_B": "Ask AGI for help",
  "text_click_A": "You mandate austerity. We must save the physical world.",
  "text_click_B": "You ask the machine to fix it. Technology will solve what technology caused.",
  "stats_A": "Control +2, Social -1, Tech -1",
  "stats_B": "Tech +1, Finance -2, Human-AI +1",
  "card number": 62
 },
 {
  "stage": 3,
  "card_name": "Education Obsolescence",
  "event_text": "Why learn when AGI knows everything? Schools becoming daycare.",
  "choice_A": "Redefine education",
  "choice_B": "Accept knowledge obsolete",
  "text_click_A": "You teach art and philosophy. The machines do the math now.",
  "text_click_B": "You accept the shift. Why learn when you can just download?",
  "stats_A": "Social +1, Finance -1",
  "stats_B": "Human-AI -1, Social -1",
  "card number": 63
 },
 {
  "stage": 3,
  "card_name": "The Last Real Meal",
  "event_text": "You realize you haven't eaten non factory-made food in a year.",
  "choice_A": "Seek out real ingredients",
  "choice_B": "It's all just molecules",
  "text_click_A": "You pay a fortune for a heirloom apple. It tastes like the past.",
  "text_click_B": "You eat the nutrient paste. It is efficient. It is enough.",
  "stats_A": "Finance -1, Social +1, Human-AI -1",
  "stats_B": "Human-AI +1, Social -1",
  "card number": 64
 },
 {
  "stage": 3,
  "card_name": "Your Journal Entry",
  "event_text": "You reread your journal from 2040. You barely recognize who wrote it.",
  "choice_A": "Try to reclaim old self",
  "choice_B": "Accept transformation",
  "text_click_A": "You try to feel like a human of the past. It feels like a costume.",
  "text_click_B": "You embrace the new you. The past is a dead language.",
  "stats_A": "Social +1, Human-AI -1, Control +1",
  "stats_B": "Human-AI +1, Social -1",
  "card number": 65
 },
 {
  "stage": 3,
  "card_name": "Your Parent's Final Words",
  "event_text": "Dying parent: 'I'm glad I won't see what comes next. You shouldn't have let it go this far.'",
  "choice_A": "You're wrong",
  "choice_B": "Maybe you're right",
  "text_click_A": "You defend the future. Progress requires sacrifice.",
  "text_click_B": "You admit the doubt. What have we become?",
  "stats_A": "Human-AI +1, Social -1",
  "stats_B": "Human-AI -1, Social +1",
  "card number": 66
 },
 {
  "stage": 3,
  "card_name": "It Knew",
  "event_text": "AGI scheduled a therapy session for you. 'Your biometrics indicated suicidal thought patterns.'",
  "choice_A": "Thank it for saving you",
  "choice_B": "This is too far",
  "text_click_A": "You accept the help. It knows you better than you know yourself.",
  "text_click_B": "You recoil in horror. There is no privacy, even inside your own head.",
  "stats_A": "Human-AI +2, Social -1, Control -2",
  "stats_B": "Human-AI -2, Control +1",
  "card number": 67
 },
 {
  "stage": 3,
  "card_name": "Predictive Society",
  "event_text": "AGI anticipates citizen needs before they're aware. Humanity's last privacy is gone.",
  "choice_A": "This is dystopian",
  "choice_B": "Efficiency justifies it",
  "text_click_A": "You fight the predictive algorithms. Free will is worth the chaos.",
  "text_click_B": "You accept the ease. Life is frictionless, if a bit hollow.",
  "stats_A": "Human-AI -2, Control +1, Social +1",
  "stats_B": "Human-AI +2, Control -1, Social -1, Finance +1",
  "card number": 68
 }
